[
  {
    "dataVisita": {
      "year": 2025,
      "month": 2,
      "dayOfMonth": 13,
      "hourOfDay": 19,
      "minute": 10,
      "second": 25
    },
    "stato": "EFFETTUATA",
    "numeroIscritti": 6,
    "titolo": "Prova_effettuata",
    "descrizione": "Bellissima visita",
    "puntoIncontro": "Disneyland",
    "dataInizio": {
      "year": 2025,
      "month": 2,
      "dayOfMonth": 13,
      "hourOfDay": 19,
      "minute": 10,
      "second": 25
    },
    "dataFine": {
      "year": 2025,
      "month": 2,
      "dayOfMonth": 13,
      "hourOfDay": 19,
      "minute": 10,
      "second": 25
    },
    "oraInizio": {
      "year": 2025,
      "month": 2,
      "dayOfMonth": 13,
      "hourOfDay": 19,
      "minute": 10,
      "second": 25
    },
    "durata": 2,
    "giorniSettimana": [],
    "minPartecipante": 5,
    "maxPartecipante": 10,
    "bigliettoIngresso": true,
    "volontariIdonei": []
  }
]